LICENSE
MANIFEST.in
README.md
pytest.ini
requirements.txt
setup.cfg
setup.py
src/leapchain/__init__.py
src/leapchain.egg-info/PKG-INFO
src/leapchain.egg-info/SOURCES.txt
src/leapchain.egg-info/dependency_links.txt
src/leapchain.egg-info/requires.txt
src/leapchain.egg-info/top_level.txt
src/leapchain/accounts/__init__.py
src/leapchain/accounts/key_files.py
src/leapchain/accounts/manage.py
src/leapchain/argparser/__init__.py
src/leapchain/argparser/validators.py
src/leapchain/base_classes/__init__.py
src/leapchain/base_classes/fetch_primary_validator_config.py
src/leapchain/base_classes/initialize_node.py
src/leapchain/blocks/__init__.py
src/leapchain/blocks/block.py
src/leapchain/blocks/signatures.py
src/leapchain/constants/__init__.py
src/leapchain/constants/clean.py
src/leapchain/constants/crawl.py
src/leapchain/constants/errors.py
src/leapchain/constants/network.py
src/leapchain/environment/__init__.py
src/leapchain/environment/environment_variables.py
src/leapchain/factories/__init__.py
src/leapchain/factories/confirmation_service.py
src/leapchain/factories/created_modified.py
src/leapchain/factories/network_node.py
src/leapchain/factories/network_transaction.py
src/leapchain/factories/network_validator.py
src/leapchain/models/__init__.py
src/leapchain/models/confirmation_service.py
src/leapchain/models/created_modified.py
src/leapchain/models/network_node.py
src/leapchain/models/network_transaction.py
src/leapchain/models/network_validator.py
src/leapchain/serializers/__init__.py
src/leapchain/serializers/account_balance.py
src/leapchain/serializers/account_locked.py
src/leapchain/serializers/configuration.py
src/leapchain/serializers/confirmation_block_message.py
src/leapchain/serializers/message.py
src/leapchain/serializers/network_block.py
src/leapchain/serializers/network_transaction.py
src/leapchain/serializers/primary_validator.py
src/leapchain/third_party/__init__.py
src/leapchain/third_party/django_redis/__init__.py
src/leapchain/third_party/django_redis/pool.py
src/leapchain/third_party/factory/__init__.py
src/leapchain/third_party/factory/utils.py
src/leapchain/third_party/pytest/__init__.py
