Metadata-Version: 2.1
Name: leapchain
Version: 0.2.5
Summary: UNKNOWN
Home-page: https://github.com/Leacpchain/leapchain-python
Author: Leapchain
Author-email: contact@theleapchain.com
Maintainer: LeapChain
License: MIT
Platform: UNKNOWN
Requires-Python: >=3.7
